{
  "N6": {
    "Distancia": 2,
    "Transporte": {
      "Taxi": {
        "NombreCompania": "Taxis Veracruz",
        "PlacaTaxi": "VRC-456",
        "Conductor": {
          "Id": "5-3894-4587",
          "Nombre": "Jairo",
          "Apellido": "Arguedas"
        },
        "PrecioKM": 1,
        "Ruta": {
          "Origen": "N8",
          "Destino": "N6"
        }
      },
      "Bus": {
        "NombreCompania": "Buses Altopalo",
        "ConductorAsignado": "Carmen Teller",
        "Ruta": {
          "Origen": "N8",
          "Destino": "N6"
        },
        "Capacidad": 80,
        "AsignacionPlazas": 71,
        "Tarifa": 255
      }
    }
  },
  "N16": {
    "Distancia": 0.30,
    "Transporte": {
      "Taxi": {
        "NombreCompania": "Taxis Hazard",
        "PlacaTaxi": "HZD-652",
        "Conductor": {
          "Id": "6-8956-8974",
          "Nombre": "Danielle",
          "Apellido": "Bregolli"
        },
        "PrecioKM": 1.30,
        "Ruta": {
          "Origen": "N8",
          "Destino": "N16"
        }
      },
      "Bus": {
        "NombreCompania": "Buses Hipster",
        "ConductorAsignado": "Daniel Amadeus",
        "Ruta": {
          "Origen": "N8",
          "Destino": "N16"
        },
        "Capacidad": 45,
        "AsignacionPlazas": 25,
        "Tarifa": 215
      }
    }
  },
  "N22": {
    "Distancia": 1.80,
    "Transporte": {
      "Taxi": {
        "NombreCompania": "Taxis Hazard",
        "PlacaTaxi": "HZD-689",
        "Conductor": {
          "Id": "3-8066-8568",
          "Nombre": "Lorna",
          "Apellido": "Blanco"
        },
        "PrecioKM": 1.30,
        "Ruta": {
          "Origen": "N16",
          "Destino": "N8"
        }
      },
      "Bus": {
        "NombreCompania": "Buses Hipster",
        "ConductorAsignado": "Cornelius Filch",
        "Ruta": {
          "Origen": "N16",
          "Destino": "N8"
        },
        "Capacidad": 45,
        "AsignacionPlazas": 40,
        "Tarifa": 215
      }
    }
  }
}